cstore/__init__.py
cstore/cli.py
cstore/constants.py
cstore/database.py
cstore/models.py
cstore/schemes.py
cstore/verbose.py
cstore/repo/__init__.py
cstore/repo/repo_command.py
cstore/repo/repo_tag.py
cstore-0.6.10.dist-info/LICENSE
cstore-0.6.10.dist-info/METADATA
cstore-0.6.10.dist-info/WHEEL
cstore-0.6.10.dist-info/entry_points.txt
cstore-0.6.10.dist-info/top_level.txt
cstore-0.6.10.dist-info/RECORD
