Metadata-Version: 2.1
Name: cstore
Version: 0.6.10
Summary: A tools to store and recall useful commands, specifically created to assist forgetful individuals
Author-email: Navid Arabi <navidved@gmail.com>
Project-URL: Bug Tracker, https://github.com/navidved/ctore/issues
Project-URL: Homepage, https://github.com/navidved/ctore
Project-URL: Documentation, https://github.com/navidved/ctore
Project-URL: Repository, https://github.com/navidved/ctore
Classifier: Programming Language :: Python :: 3
Classifier: License :: OSI Approved :: MIT License
Classifier: Operating System :: OS Independent
Requires-Python: >=3.8
License-File: LICENSE
Requires-Dist: rich (==13.4.2)
Requires-Dist: cryptocode (==0.1)
Requires-Dist: SQLAlchemy (==2.0.16)
Requires-Dist: pydantic (==1.8)
Requires-Dist: typer[all] (==0.9.0)
Requires-Dist: simple-term-menu (==1.6.1)
Requires-Dist: clipboard (==0.0.4)
